test.py
pyigdl/__init__.py
pyigdl/igdl.py
pyigdl/utils.py
pyigdl-0.0.14.dist-info/LICENSE
pyigdl-0.0.14.dist-info/METADATA
pyigdl-0.0.14.dist-info/WHEEL
pyigdl-0.0.14.dist-info/top_level.txt
pyigdl-0.0.14.dist-info/RECORD
