Metadata-Version: 2.1
Name: pyigdl
Version: 0.0.14
Summary: A Python package for downloading Instagram videos, posts, stories, and more. This package provides an unofficial scraping functionality to retrieve content from Instagram, similar to saveig.app and https://github.com/sasmeee/igdl (Node.Js)
Author-email: Vasu Goel <goelvasu1999@gmail.com>
Project-URL: Homepage, https://github.com/crypticguy/pyigdl
Project-URL: Issues, https://github.com/pypa/crypticguy/pyigdl
Keywords: Instagram,Download,Reels,Videos,Media,Photos,Fetch
Classifier: Programming Language :: Python :: 3
Classifier: License :: OSI Approved :: MIT License
Classifier: Operating System :: OS Independent
Requires-Python: >=3.8
License-File: LICENSE
Requires-Dist: parsel
Requires-Dist: brotli
Requires-Dist: requests
